{
  "m_GameObject": {
    "m_FileID": 0,
    "m_PathID": 283
  },
  "m_Enabled": 1,
  "m_Script": {
    "m_FileID": 3,
    "m_PathID": 256
  },
  "m_Name": "",
  "curve": {
    "m_FileID": 0,
    "m_PathID": 0
  },
  "overrideCurve": {
    "m_FileID": 0,
    "m_PathID": 0
  },
  "matchTag": "",
  "position": 0.606413662,
  "distanceBasedPosition": 1,
  "autoLookDirection": 1,
  "target": {
    "m_FileID": 0,
    "m_PathID": 568
  },
  "roll": 0.0,
  "overrideTarget": {
    "m_FileID": 0,
    "m_PathID": 0
  },
  "debugLookPos": {
    "x": -0.149500251,
    "y": 1.477646,
    "z": -1.37993026
  },
  "softFocus": 0,
  "targetFocusStrength": 2.0
}