{
  "m_GameObject": {
    "m_FileID": 0,
    "m_PathID": 11
  },
  "m_Enabled": 1,
  "m_Script": {
    "m_FileID": 21,
    "m_PathID": 264
  },
  "m_Name": "",
  "explodableBits": [
    {
      "m_FileID": 0,
      "m_PathID": 511
    },
    {
      "m_FileID": 0,
      "m_PathID": 1399
    },
    {
      "m_FileID": 0,
      "m_PathID": 659
    },
    {
      "m_FileID": 0,
      "m_PathID": 554
    }
  ],
  "destroyDelay": 1.0,
  "explodeDirection": {
    "x": 0.27,
    "y": 0.0,
    "z": 0.41
  },
  "force": 30.0,
  "disableRandomly": 0
}