{
  "m_GameObject": {
    "m_FileID": 0,
    "m_PathID": 323
  },
  "m_Enabled": 1,
  "m_Script": {
    "m_FileID": 21,
    "m_PathID": 264
  },
  "m_Name": "",
  "explodableBits": [
    {
      "m_FileID": 0,
      "m_PathID": 1567
    },
    {
      "m_FileID": 0,
      "m_PathID": 573
    },
    {
      "m_FileID": 0,
      "m_PathID": 802
    },
    {
      "m_FileID": 0,
      "m_PathID": 396
    },
    {
      "m_FileID": 0,
      "m_PathID": 1039
    },
    {
      "m_FileID": 0,
      "m_PathID": 1335
    },
    {
      "m_FileID": 0,
      "m_PathID": 805
    }
  ],
  "destroyDelay": 1.0,
  "explodeDirection": {
    "x": -0.16,
    "y": 0.0,
    "z": 0.95
  },
  "force": 30.0,
  "disableRandomly": 0
}