{
  "m_GameObject": {
    "m_FileID": 0,
    "m_PathID": 840
  },
  "m_Enabled": 1,
  "m_Script": {
    "m_FileID": 21,
    "m_PathID": 264
  },
  "m_Name": "",
  "explodableBits": [
    {
      "m_FileID": 0,
      "m_PathID": 1866
    },
    {
      "m_FileID": 0,
      "m_PathID": 1590
    },
    {
      "m_FileID": 0,
      "m_PathID": 265
    },
    {
      "m_FileID": 0,
      "m_PathID": 763
    },
    {
      "m_FileID": 0,
      "m_PathID": 744
    },
    {
      "m_FileID": 0,
      "m_PathID": 1479
    },
    {
      "m_FileID": 0,
      "m_PathID": 1054
    }
  ],
  "destroyDelay": 1.0,
  "explodeDirection": {
    "x": 0.1,
    "y": 0.0,
    "z": 0.95
  },
  "force": 30.0,
  "disableRandomly": 1
}