{
  "m_GameObject": {
    "m_FileID": 0,
    "m_PathID": 228
  },
  "m_Enabled": 1,
  "m_Script": {
    "m_FileID": 22,
    "m_PathID": 264
  },
  "m_Name": "",
  "explodableBits": [
    {
      "m_FileID": 0,
      "m_PathID": 251
    },
    {
      "m_FileID": 0,
      "m_PathID": 664
    },
    {
      "m_FileID": 0,
      "m_PathID": 1533
    },
    {
      "m_FileID": 0,
      "m_PathID": 1023
    }
  ],
  "destroyDelay": 1.0,
  "explodeDirection": {
    "x": -0.01,
    "y": 0.0,
    "z": 0.74
  },
  "force": 30.0,
  "disableRandomly": 1
}