{
  "m_GameObject": {
    "m_FileID": 0,
    "m_PathID": 1147
  },
  "m_Enabled": 1,
  "m_Script": {
    "m_FileID": 2,
    "m_PathID": 892
  },
  "m_Name": "",
  "AttackMaterial": {
    "m_FileID": 0,
    "m_PathID": 14
  },
  "HealMaterial": {
    "m_FileID": 0,
    "m_PathID": 15
  },
  "AttackColor": {
    "r": 0.6862745,
    "g": 0.0,
    "b": 0.0,
    "a": 1.0
  },
  "HealColor": {
    "r": 0.141176477,
    "g": 0.784313738,
    "b": 0.0,
    "a": 1.0
  },
  "TotalTime": 0.3,
  "TotalTintTime": 0.25,
  "EffectHeight": 32.0
}